vsts/__init__.py
vsts/cli/__init__.py
vsts/cli/common/__init__.py
vsts/cli/common/_credentials.py
vsts/cli/common/arguments.py
vsts/cli/common/config.py
vsts/cli/common/configure.py
vsts/cli/common/file_cache.py
vsts/cli/common/git.py
vsts/cli/common/identities.py
vsts/cli/common/operations.py
vsts/cli/common/services.py
vsts/cli/common/uri.py
vsts/cli/common/uuid.py
vsts/cli/common/version.py
vsts/cli/common/vsts_git_url_info.py
vsts/cli/tests/__init__.py
vsts/cli/tests/test_arguments.py
vsts/cli/tests/test_configure.py
vsts/cli/tests/test_credentials.py
vsts/cli/tests/test_uuid.py
vsts/cli/tests/test_version.py
vsts_cli_common-0.1.4.dist-info/LICENSE.txt
vsts_cli_common-0.1.4.dist-info/METADATA
vsts_cli_common-0.1.4.dist-info/WHEEL
vsts_cli_common-0.1.4.dist-info/top_level.txt
vsts_cli_common-0.1.4.dist-info/RECORD
